akshare_two/__init__.py
akshare_two/eastmoney/client.py
akshare_two/eastmoney/utils.py
akshare_two/indicators.py
akshare_two/modules/analysis/__init__.py
akshare_two/modules/analysis/base.py
akshare_two/modules/analysis/eastmoney.py
akshare_two/modules/analysis/factory.py
akshare_two/modules/cache.py
akshare_two/modules/financial/base.py
akshare_two/modules/financial/eastmoney_direct.py
akshare_two/modules/financial/factory.py
akshare_two/modules/financial/sina.py
akshare_two/modules/historical/base.py
akshare_two/modules/historical/eastmoney.py
akshare_two/modules/historical/eastmoney_direct.py
akshare_two/modules/historical/factory.py
akshare_two/modules/historical/sina.py
akshare_two/modules/historical/sina_direct.py
akshare_two/modules/indicators/__init__.py
akshare_two/modules/indicators/base.py
akshare_two/modules/indicators/factory.py
akshare_two/modules/indicators/simple.py
akshare_two/modules/indicators/talib.py
akshare_two/modules/info/base.py
akshare_two/modules/info/eastmoney.py
akshare_two/modules/info/eastmoney_direct.py
akshare_two/modules/info/factory.py
akshare_two/modules/insider/base.py
akshare_two/modules/insider/factory.py
akshare_two/modules/insider/xueqiu.py
akshare_two/modules/insider/xueqiu_direct.py
akshare_two/modules/market/__init__.py
akshare_two/modules/market/base.py
akshare_two/modules/market/eastmoney.py
akshare_two/modules/market/factory.py
akshare_two/modules/news/base.py
akshare_two/modules/news/eastmoney.py
akshare_two/modules/news/factory.py
akshare_two/modules/realtime/base.py
akshare_two/modules/realtime/eastmoney.py
akshare_two/modules/realtime/eastmoney_direct.py
akshare_two/modules/realtime/factory.py
akshare_two/modules/realtime/xueqiu.py
akshare_two/modules/realtime/xueqiu_direct.py
akshare_two/modules/utils.py
akshare_two/py.typed
akshare_two/sina/__init__.py
akshare_two/sina/client.py
akshare_two/xueqiu/__init__.py
akshare_two/xueqiu/client.py
akshare_two-1.0.0.dist-info/WHEEL
akshare_two-1.0.0.dist-info/METADATA
akshare_two-1.0.0.dist-info/RECORD
