Metadata-Version: 2.4
Name: akshare-two
Version: 1.0.0
Summary: Standardized interface for Chinese financial market data, built on AKShare with unified data formats and simplified APIs
Keywords: akshare,financial-data,stock-data,quant
License-Expression: MIT
Requires-Dist: pandas>=2.0.0
Requires-Dist: requests>=2.31.0
Requires-Dist: cachetools>=5.5.0
Requires-Dist: ta-lib>=0.6.4 ; extra == 'talib'
Requires-Python: >=3.10
Project-URL: Homepage, https://github.com/stdeson/akshare-two
Project-URL: Repository, https://github.com/stdeson/akshare-two.git
Provides-Extra: talib
